presidio_cli/__init__.py
presidio_cli/__main__.py
presidio_cli/analyzer.py
presidio_cli/cli.py
presidio_cli/config.py
presidio_cli/conf/default.yaml
presidio_cli/conf/limited.yaml
presidio_cli-0.0.8.dist-info/LICENSE
presidio_cli-0.0.8.dist-info/METADATA
presidio_cli-0.0.8.dist-info/WHEEL
presidio_cli-0.0.8.dist-info/entry_points.txt
presidio_cli-0.0.8.dist-info/top_level.txt
presidio_cli-0.0.8.dist-info/RECORD
