Metadata-Version: 2.1
Name: presidio-cli
Version: 0.0.8
Summary: An python CLI for analyze PII Entities with Microsoft Presidio framework.
Home-page: https://github.com/insightsengineering/presidio-cli
Author: Insights Engineering
Author-email: basel.nestcicd@roche.com
License: Apache 2.0
Keywords: pii,checker
Classifier: Programming Language :: Python :: 3.8
Classifier: Programming Language :: Python :: 3.9
Classifier: Programming Language :: Python :: 3.10
Classifier: License :: OSI Approved :: Apache Software License
Classifier: Operating System :: OS Independent
Requires-Python: >=3.7
License-File: LICENSE
Requires-Dist: presidio-analyzer (>=2.2)
Requires-Dist: pyyaml
Requires-Dist: pathspec
